img_url_replace/__init__.py
img_url_replace/img_upload.py
img_url_replace/parse_md.py
test/__init__.py
test/test_upload.py
replace_md_img-0.0.14.dist-info/LICENSE
replace_md_img-0.0.14.dist-info/METADATA
replace_md_img-0.0.14.dist-info/WHEEL
replace_md_img-0.0.14.dist-info/entry_points.txt
replace_md_img-0.0.14.dist-info/top_level.txt
replace_md_img-0.0.14.dist-info/RECORD
