Metadata-Version: 2.1
Name: replace-md-img
Version: 0.0.14
Summary: 一个python脚本，用来将markdown中的图片上传到图床上，并替换文档中的链接
Home-page: https://github.com/ggqshr/replace_img_md
Author: ggq
Author-email: ggq18663278150@gmail.com
License: UNKNOWN
Platform: UNKNOWN
Requires-Dist: tqdm
Requires-Dist: requests
Requires-Dist: click
